AUTHORS.rst
CONTRIBUTING.rst
HISTORY.rst
LICENSE
MANIFEST.in
README.rst
setup.cfg
setup.py
collectfaster/__init__.py
collectfaster/backends/__init__.py
collectfaster/backends/boto.py
collectfaster/backends/boto3.py
collectfaster/management/__init__.py
collectfaster/management/commands/__init__.py
collectfaster/management/commands/collectstatic.py
django_collectfaster.egg-info/PKG-INFO
django_collectfaster.egg-info/SOURCES.txt
django_collectfaster.egg-info/dependency_links.txt
django_collectfaster.egg-info/not-zip-safe
django_collectfaster.egg-info/requires.txt
django_collectfaster.egg-info/top_level.txt