Metadata-Version: 1.1
Name: django-collectfaster
Version: 0.1.3
Summary: Parallel file copying for Django's collectstatic.
Home-page: https://github.com/dreipol/django-collectfaster
Author: dreipol GmbH
Author-email: dev@dreipol.ch
License: BSD
Keywords: django-collectfaster
Platform: UNKNOWN
Classifier: Development Status :: 3 - Alpha
Classifier: Framework :: Django
Classifier: Framework :: Django :: 1.8
Classifier: Framework :: Django :: 1.9
Classifier: Intended Audience :: Developers
Classifier: License :: OSI Approved :: BSD License
Classifier: Natural Language :: English
Classifier: Programming Language :: Python :: 2
Classifier: Programming Language :: Python :: 2.7
Classifier: Programming Language :: Python :: 3
Classifier: Programming Language :: Python :: 3.3
Classifier: Programming Language :: Python :: 3.4
Classifier: Programming Language :: Python :: 3.5
